leaklock/__init__.py
leaklock/cli.py
leaklock/secret_scanner.py
leaklock-0.1.0.dist-info/METADATA
leaklock-0.1.0.dist-info/WHEEL
leaklock-0.1.0.dist-info/entry_points.txt
leaklock-0.1.0.dist-info/top_level.txt
leaklock-0.1.0.dist-info/RECORD
