Metadata-Version: 2.4
Name: leaklock
Version: 0.1.0
Summary: Stops API key leaks by blocking commits with secrets before they reach GitHub.
Author-email: Ahmed Muawia <amuawia666@email.com>
License: MIT
Classifier: Programming Language :: Python :: 3
Classifier: License :: OSI Approved :: MIT License
Requires-Python: >=3.8
